libsfst.so
sfst.cpython-311-x86_64-linux-gnu.so
sfst-1.8.0.dist-info/RECORD
sfst-1.8.0.dist-info/METADATA
sfst-1.8.0.dist-info/top_level.txt
sfst-1.8.0.dist-info/WHEEL
sfst-1.8.0.dist-info/licenses/COPYING
