Metadata-Version: 2.4
Name: sfst
Version: 1.8.0
Summary: Python binding for SFST
Home-page: https://github.com/santhoshtr/sfst
Author: Santhosh Thottingal
Author-email: santhosh.thottingal@gmail.com
License: GPLv2
Requires-Python: >3.8.0
License-File: COPYING
Dynamic: author
Dynamic: author-email
Dynamic: description
Dynamic: description-content-type
Dynamic: home-page
Dynamic: license
Dynamic: license-file
Dynamic: requires-python
Dynamic: summary
